maya/__init__.py
maya/__version__.py
maya/compat.py
maya/core.py
maya-0.6.0.dist-info/DESCRIPTION.rst
maya-0.6.0.dist-info/METADATA
maya-0.6.0.dist-info/RECORD
maya-0.6.0.dist-info/WHEEL
maya-0.6.0.dist-info/metadata.json
maya-0.6.0.dist-info/top_level.txt
