Metadata-Version: 2.0
Name: maya
Version: 0.6.0
Summary: Datetimes for Humans.
Home-page: https://github.com/kennethreitz/maya
Author: Kenneth Reitz
Author-email: me@kennethreitz.org
License: MIT
Platform: UNKNOWN
Classifier: Development Status :: 5 - Production/Stable
Classifier: Intended Audience :: Developers
Classifier: License :: OSI Approved :: MIT License
Classifier: Natural Language :: English
Classifier: Operating System :: OS Independent
Classifier: Programming Language :: Python :: 2
Classifier: Programming Language :: Python :: 2.7
Classifier: Programming Language :: Python :: 3
Classifier: Programming Language :: Python :: 3.6
Classifier: Programming Language :: Python :: Implementation
Classifier: Programming Language :: Python :: Implementation :: CPython
Classifier: Topic :: Software Development :: Libraries :: Python Modules
Requires-Dist: humanize
Requires-Dist: pytz
Requires-Dist: dateparser (>=0.7.0)
Requires-Dist: tzlocal
Requires-Dist: pendulum (>=2.0.2)
Requires-Dist: snaptime
